cogni/__init__.py
cogni/agent.py
cogni/config/__init__.py
cogni/config/emotions.py
cogni/config/personalities.py
cogni/config/safety.py
cogni/core/__init__.py
cogni/core/emotional_engine.py
cogni/core/memory_store.py
cogni/core/social_registry.py
cogni/models/__init__.py
cogni/models/amygdala.py
cogni/models/vertex_ai.py
cogni/utils/__init__.py
cogni/utils/logger.py
cogni/utils/parser.py
cogni_59-1.0.0.dist-info/licenses/LICENSE
cogni_59-1.0.0.dist-info/METADATA
cogni_59-1.0.0.dist-info/WHEEL
cogni_59-1.0.0.dist-info/top_level.txt
cogni_59-1.0.0.dist-info/RECORD
