Metadata-Version: 2.4
Name: cogni-59
Version: 1.0.0
Summary: A production-ready Python library for emotional AI agents
Home-page: https://github.com/ndhaliwal59/cogni
Author: Nishan
Author-email: ndhaliwal0659@gmail.com
Classifier: Development Status :: 4 - Beta
Classifier: Intended Audience :: Developers
Classifier: Topic :: Software Development :: Libraries :: Python Modules
Classifier: Topic :: Scientific/Engineering :: Artificial Intelligence
Classifier: License :: OSI Approved :: MIT License
Classifier: Programming Language :: Python :: 3
Classifier: Programming Language :: Python :: 3.8
Classifier: Programming Language :: Python :: 3.9
Classifier: Programming Language :: Python :: 3.10
Classifier: Programming Language :: Python :: 3.11
Requires-Python: >=3.8
License-File: LICENSE
Requires-Dist: torch>=2.0.0
Requires-Dist: faiss-cpu>=1.7.4
Requires-Dist: transformers>=4.30.0
Requires-Dist: google-cloud-aiplatform>=1.38.0
Requires-Dist: python-dotenv>=1.0.0
Requires-Dist: numpy>=1.24.0
Dynamic: author
Dynamic: author-email
Dynamic: classifier
Dynamic: description
Dynamic: description-content-type
Dynamic: home-page
Dynamic: license-file
Dynamic: requires-dist
Dynamic: requires-python
Dynamic: summary
